setupa.py
esdk_obs_python233.egg-info/PKG-INFO
esdk_obs_python233.egg-info/SOURCES.txt
esdk_obs_python233.egg-info/dependency_links.txt
esdk_obs_python233.egg-info/not-zip-safe
esdk_obs_python233.egg-info/top_level.txt