Metadata-Version: 1.0
Name: esdk-obs-python233
Version: 3.20.11
Summary: OBS Python SDK
Home-page: http://obs-browser.obs.myhuaweicloud.com
Author: UNKNOWN
Author-email: UNKNOWN
License: Apache-2.0
Keywords: python obs
Platform: UNKNOWN
